polynomiograpy/__init__.py
polynomiograpy/cli/__init__.py
polynomiograpy/common/__init__.py
polynomiograpy/common/finite_field.py
polynomiograpy/common/polynomial.py
polynomiograpy/iterations/__init__.py
polynomiograpy/iterations/helpers.py
polynomiograpy/iterations/methods.py
polynomiograpy/roots/__init__.py
polynomiograpy/roots/helpers.py
polynomiograpy-0.5.0.dist-info/LICENSE
polynomiograpy-0.5.0.dist-info/METADATA
polynomiograpy-0.5.0.dist-info/WHEEL
polynomiograpy-0.5.0.dist-info/entry_points.txt
polynomiograpy-0.5.0.dist-info/RECORD
