Metadata-Version: 2.1
Name: polynomiograpy
Version: 0.5.0
Summary: 
Home-page: https://github.com/ismltpn/polynomiograpy/
License: MIT
Keywords: Polynomiography,Polynomials,Visual Art
Author: İsmail Tapan
Author-email: ismltpn@gmail.com
Maintainer: İsmail Tapan
Maintainer-email: ismltpn@gmail.com
Requires-Python: >=3.9,<4.0
Classifier: License :: OSI Approved :: MIT License
Classifier: Programming Language :: Python :: 3
Classifier: Programming Language :: Python :: 3.9
Classifier: Programming Language :: Python :: 3.10
Classifier: Programming Language :: Python :: 3.11
Requires-Dist: dearpygui[gui] (>=1.9.1,<2.0.0)
Requires-Dist: numpy (>=1.24.2,<2.0.0)
Requires-Dist: pillow (>=9.4.0,<10.0.0)
Project-URL: Repository, https://github.com/ismltpn/polynomiograpy/
